im_just_varun_not_yughandar/__init__.py
im_just_varun_not_yughandar-1.4.3.dist-info/LICENCE.txt
im_just_varun_not_yughandar-1.4.3.dist-info/METADATA
im_just_varun_not_yughandar-1.4.3.dist-info/WHEEL
im_just_varun_not_yughandar-1.4.3.dist-info/top_level.txt
im_just_varun_not_yughandar-1.4.3.dist-info/RECORD
