Metadata-Version: 2.1
Name: im-just-varun-not-yughandar
Version: 1.4.3
Summary: Marry Christmas
Home-page: UNKNOWN
Author: Santa
Author-email: varun1@gmail.com
License: UNKNOWN
Platform: UNKNOWN
Classifier: Programming Language :: Python :: 3
Classifier: License :: OSI Approved :: MIT License
Classifier: Operating System :: OS Independent
